/*
** $Id: lvm.c,v 2.63.1.5 2011/08/17 20:43:11 roberto Exp $
** Lua virtual machine
** See Copyright Notice in lua.h
*/


#include <stdio.h>
#include <stdlib.h>
#include <string.h>

#define lvm_c
#define LUA_CORE

#include "lua.h"

#include "ldebug.h"
#include "ldo.h"
#include "lfunc.h"
#include "lgc.h"
#include "lobject.h"
#include "lopcodes.h"
#include "lstate.h"
#include "lstring.h"
#include "ltable.h"
#include "ltm.h"
#include "lvm.h"



/* limit for table tag-method chains (to avoid loops) */
#define MAXTAGLOOP	100

/* number,string-->number */
const TValue *luaV_tonumber (const TValue *obj, TValue *n) {
  lua_Number num;
  if (ttisnumber(obj)) return obj;
  if (ttisstring(obj) && luaO_str2d(svalue(obj), &num)) {
    setnvalue(n, num);
    return n;
  }
  else
    return NULL;
}

/* number->string */
int luaV_tostring (lua_State *L, StkId obj) {
  if (!ttisnumber(obj))
    return 0;
  else {
    char s[LUAI_MAXNUMBER2STR];
    lua_Number n = nvalue(obj);
    lua_number2str(s, n);
    setsvalue2s(L, obj, luaS_new(L, s));
    return 1;
  }
}

/* 判断调试MASK是否设置，以及相关条件是否已满足，满足则进入钩子函数 */
static void traceexec (lua_State *L, const Instruction *pc) {
  lu_byte mask = L->hookmask;
  const Instruction *oldpc = L->savedpc;
  L->savedpc = pc;
  if ((mask & LUA_MASKCOUNT) && L->hookcount == 0) {	/* 执行了指定数量的pc，调用指定的钩子函数 */
    resethookcount(L);
    luaD_callhook(L, LUA_HOOKCOUNT, -1);
  }
  if (mask & LUA_MASKLINE) {	/* LUA_MASKLINE不是说执行到了某一行，具体的意思看下面的代码 */
    Proto *p = ci_func(L->ci)->l.p;
    int npc = pcRel(pc, p);
    int newline = getline(p, npc);
    /* call linehook when enter a new function, when jump back (loop),
       or when enter a new line */
    if (npc == 0 || pc <= oldpc || newline != getline(p, pcRel(oldpc, p)))
      luaD_callhook(L, LUA_HOOKLINE, newline);
  }
}

/* 调用元方法，将结果返回给res */
static void callTMres (lua_State *L, StkId res, const TValue *f,
                        const TValue *p1, const TValue *p2) {
  ptrdiff_t result = savestack(L, res);
  setobj2s(L, L->top, f);  /* push function */
  setobj2s(L, L->top+1, p1);  /* 1st argument */
  setobj2s(L, L->top+2, p2);  /* 2nd argument */
  luaD_checkstack(L, 3);
  L->top += 3;
  luaD_call(L, L->top - 3, 1);
  res = restorestack(L, result);
  L->top--;
  setobjs2s(L, res, L->top);
}



static void callTM (lua_State *L, const TValue *f, const TValue *p1,
                    const TValue *p2, const TValue *p3) {
  setobj2s(L, L->top, f);  /* push function */
  setobj2s(L, L->top+1, p1);  /* 1st argument */
  setobj2s(L, L->top+2, p2);  /* 2nd argument */
  setobj2s(L, L->top+3, p3);  /* 3th argument */
  luaD_checkstack(L, 4);
  L->top += 4;
  luaD_call(L, L->top - 4, 0);
}


void luaV_gettable (lua_State *L, const TValue *t, TValue *key, StkId val) {
  int loop;
  for (loop = 0; loop < MAXTAGLOOP; loop++) {
    const TValue *tm;
    if (ttistable(t)) {  /* `t' is a table? */
      Table *h = hvalue(t);
      const TValue *res = luaH_get(h, key); /* do a primitive get */
      if (!ttisnil(res) ||  /* result is no nil? */
          (tm = fasttm(L, h->metatable, TM_INDEX)) == NULL) { /* or no TM? */
        setobj2s(L, val, res);
        return;
      }
      /* else will try the tag method */
    }
    else if (ttisnil(tm = luaT_gettmbyobj(L, t, TM_INDEX)))
      luaG_typeerror(L, t, "index");
    if (ttisfunction(tm)) {
      callTMres(L, val, tm, t, key);
      return;
    }
    t = tm;  /* else repeat with `tm' */ 
  }
  luaG_runerror(L, "loop in gettable");
}


void luaV_settable (lua_State *L, const TValue *t, TValue *key, StkId val) {
  int loop;
  TValue temp;
  for (loop = 0; loop < MAXTAGLOOP; loop++) {
    const TValue *tm;
    if (ttistable(t)) {  /* `t' is a table? */
      Table *h = hvalue(t);
      TValue *oldval = luaH_set(L, h, key); /* do a primitive set */
      if (!ttisnil(oldval) ||  /* result is no nil? */
          (tm = fasttm(L, h->metatable, TM_NEWINDEX)) == NULL) { /* or no TM? */
        setobj2t(L, oldval, val);
        h->flags = 0;	/* 更新flags:假设所有的tm都存在 */
        luaC_barriert(L, h, val);
        return;
      }
      /* else will try the tag method */
    }
    else if (ttisnil(tm = luaT_gettmbyobj(L, t, TM_NEWINDEX)))
      luaG_typeerror(L, t, "index");
    if (ttisfunction(tm)) {
      callTM(L, tm, t, key, val);
      return;
    }
    /* else repeat with `tm' */
    setobj(L, &temp, tm);  /* avoid pointing inside table (may rehash) */
    t = &temp;
  }
  luaG_runerror(L, "loop in settable");
}

/* 同上callTM，针对tblA+tblB这种两个操作数的，尝试调用特定元方法 */
static int call_binTM (lua_State *L, const TValue *p1, const TValue *p2,
                       StkId res, TMS event) {
  const TValue *tm = luaT_gettmbyobj(L, p1, event);  /* try first operand */
  if (ttisnil(tm))
    tm = luaT_gettmbyobj(L, p2, event);  /* try second operand */
  if (ttisnil(tm)) return 0;
  callTMres(L, res, tm, p1, p2);
  return 1;
}

/* only for userdata */
static const TValue *get_compTM (lua_State *L, Table *mt1, Table *mt2,
                                  TMS event) {
  const TValue *tm1 = fasttm(L, mt1, event);
  const TValue *tm2;
  if (tm1 == NULL) return NULL;  /* no metamethod */
  if (mt1 == mt2) return tm1;  /* same metatables => same metamethods */
  tm2 = fasttm(L, mt2, event);
  if (tm2 == NULL) return NULL;  /* no metamethod */
  if (luaO_rawequalObj(tm1, tm2))  /* same metamethods? */
    return tm1;
  return NULL;
}

/* 元方法：比较操作 */
static int call_orderTM (lua_State *L, const TValue *p1, const TValue *p2,
                         TMS event) {
  const TValue *tm1 = luaT_gettmbyobj(L, p1, event);
  const TValue *tm2;
  if (ttisnil(tm1)) return -1;  /* no metamethod? */
  tm2 = luaT_gettmbyobj(L, p2, event);
  if (!luaO_rawequalObj(tm1, tm2))  /* different metamethods? */
    return -1;
  callTMres(L, L->top, tm1, p1, p2);
  return !l_isfalse(L->top);
}


static int l_strcmp (const TString *ls, const TString *rs) {
  const char *l = getstr(ls);
  size_t ll = ls->tsv.len;
  const char *r = getstr(rs);
  size_t lr = rs->tsv.len;
  for (;;) {
    int temp = strcoll(l, r);	/* 依环境变量 LC_COLLATE 所指定的文字排列次序来比较 s1 和 s2 字符串 */
    if (temp != 0) return temp;
    else {  /* strings are equal up to a `\0' */
      size_t len = strlen(l);  /* index of first `\0' in both strings */
      if (len == lr)  /* r is finished? */
        return (len == ll) ? 0 : 1;
      else if (len == ll)  /* l is finished? */
        return -1;  /* l is smaller than r (because r is not finished) */
      /* both strings longer than `len'; go on comparing (after the `\0') */
      len++;
      l += len; ll -= len; r += len; lr -= len;
    }
  }
}

/* 比较指令 */
int luaV_lessthan (lua_State *L, const TValue *l, const TValue *r) {
  int res;
  if (ttype(l) != ttype(r))
    return luaG_ordererror(L, l, r);
  else if (ttisnumber(l))
    return luai_numlt(nvalue(l), nvalue(r));
  else if (ttisstring(l))
    return l_strcmp(rawtsvalue(l), rawtsvalue(r)) < 0;
  else if ((res = call_orderTM(L, l, r, TM_LT)) != -1)
    return res;
  return luaG_ordererror(L, l, r);
}


static int lessequal (lua_State *L, const TValue *l, const TValue *r) {
  int res;
  if (ttype(l) != ttype(r))
    return luaG_ordererror(L, l, r);
  else if (ttisnumber(l))
    return luai_numle(nvalue(l), nvalue(r));
  else if (ttisstring(l))
    return l_strcmp(rawtsvalue(l), rawtsvalue(r)) <= 0;
  else if ((res = call_orderTM(L, l, r, TM_LE)) != -1)  /* first try `le' */
    return res;
  else if ((res = call_orderTM(L, r, l, TM_LT)) != -1)  /* else try `lt' */
    return !res;
  return luaG_ordererror(L, l, r);
}


int luaV_equalval (lua_State *L, const TValue *t1, const TValue *t2) {
  const TValue *tm;
  lua_assert(ttype(t1) == ttype(t2));
  switch (ttype(t1)) {
    case LUA_TNIL: return 1;
    case LUA_TNUMBER: return luai_numeq(nvalue(t1), nvalue(t2));
    case LUA_TBOOLEAN: return bvalue(t1) == bvalue(t2);  /* true must be 1 !! */
    case LUA_TLIGHTUSERDATA: return pvalue(t1) == pvalue(t2);
    case LUA_TUSERDATA: {
      if (uvalue(t1) == uvalue(t2)) return 1;
      tm = get_compTM(L, uvalue(t1)->metatable, uvalue(t2)->metatable,
                         TM_EQ);
      break;  /* will try TM */
    }
    case LUA_TTABLE: {
      if (hvalue(t1) == hvalue(t2)) return 1;
      tm = get_compTM(L, hvalue(t1)->metatable, hvalue(t2)->metatable, TM_EQ);
      break;  /* will try TM */
    }
    default: return gcvalue(t1) == gcvalue(t2);
  }
  if (tm == NULL) return 0;  /* no TM? */
  callTMres(L, L->top, tm, t1, t2);  /* call TM */
  return !l_isfalse(L->top);
}

/* 从last开始，一共链接total个slot          */
void luaV_concat (lua_State *L, int total, int last) {
  do {
    StkId top = L->base + last + 1;
    int n = 2;  /* number of elements handled in this pass (at least 2) */
    if (!(ttisstring(top-2) || ttisnumber(top-2)) || !tostring(L, top-1)) {
      if (!call_binTM(L, top-2, top-1, top-2, TM_CONCAT))
        luaG_concaterror(L, top-2, top-1);
    } else if (tsvalue(top-1)->len == 0)  /* second op is empty? */
      (void)tostring(L, top - 2);  /* result is first op (as string) */
    else {
      /* at least two string values; get as many as possible */
      size_t tl = tsvalue(top-1)->len;
      char *buffer;
      int i;
      /* collect total length */
      for (n = 1; n < total && tostring(L, top-n-1); n++) {
        size_t l = tsvalue(top-n-1)->len;
        if (l >= MAX_SIZET - tl) luaG_runerror(L, "string length overflow");
        tl += l;
      }
      buffer = luaZ_openspace(L, &G(L)->buff, tl);
      tl = 0;
      for (i=n; i>0; i--) {  /* concat all strings */
        size_t l = tsvalue(top-i)->len;
        memcpy(buffer+tl, svalue(top-i), l);
        tl += l;
      }
      setsvalue2s(L, top-n, luaS_newlstr(L, buffer, tl));
    }
    total -= n-1;  /* got `n' strings to create 1 new */
    last -= n-1;
  } while (total > 1);  /* repeat until only 1 result left */
}


static void Arith (lua_State *L, StkId ra, const TValue *rb,
                   const TValue *rc, TMS op) {
  TValue tempb, tempc;
  const TValue *b, *c;
  if ((b = luaV_tonumber(rb, &tempb)) != NULL &&
      (c = luaV_tonumber(rc, &tempc)) != NULL) {
    lua_Number nb = nvalue(b), nc = nvalue(c);
    switch (op) {
      case TM_ADD: setnvalue(ra, luai_numadd(nb, nc)); break;
      case TM_SUB: setnvalue(ra, luai_numsub(nb, nc)); break;
      case TM_MUL: setnvalue(ra, luai_nummul(nb, nc)); break;
      case TM_DIV: setnvalue(ra, luai_numdiv(nb, nc)); break;
      case TM_MOD: setnvalue(ra, luai_nummod(nb, nc)); break;
      case TM_POW: setnvalue(ra, luai_numpow(nb, nc)); break;
      case TM_UNM: setnvalue(ra, luai_numunm(nb)); break;
      default: lua_assert(0); break;
    }
  }
  else if (!call_binTM(L, rb, rc, ra, op))
    luaG_aritherror(L, rb, rc);
}



/*
** some macros for common tasks in `luaV_execute'
*/

#define runtime_check(L, c)	{ if (!(c)) break; }

/* 提取指令中A,B,C的值 */
#define RA(i)	(base+GETARG_A(i))
/* to be used after possible stack reallocation */
#define RB(i)	check_exp(getBMode(GET_OPCODE(i)) == OpArgR, base+GETARG_B(i))
#define RC(i)	check_exp(getCMode(GET_OPCODE(i)) == OpArgR, base+GETARG_C(i))
#define RKB(i)	check_exp(getBMode(GET_OPCODE(i)) == OpArgK, \
	ISK(GETARG_B(i)) ? k+INDEXK(GETARG_B(i)) : base+GETARG_B(i))
#define RKC(i)	check_exp(getCMode(GET_OPCODE(i)) == OpArgK, \
	ISK(GETARG_C(i)) ? k+INDEXK(GETARG_C(i)) : base+GETARG_C(i))
#define KBx(i)	check_exp(getBMode(GET_OPCODE(i)) == OpArgK, k+GETARG_Bx(i))


#define dojump(L,pc,i)	{(pc) += (i); luai_threadyield(L);}


#define Protect(x)	{ L->savedpc = pc; {x;}; base = L->base; }

/* 这个宏有意思哈 */ 
#define arith_op(op,tm) { \
        TValue *rb = RKB(i); \
        TValue *rc = RKC(i); \
        if (ttisnumber(rb) && ttisnumber(rc)) { \
          lua_Number nb = nvalue(rb), nc = nvalue(rc); \
          setnvalue(ra, op(nb, nc)); \
        } \
        else \
          Protect(Arith(L, ra, rb, rc, tm)); \
      }


/* 
** KEYCODE
** nexeccalls:Lua连续调用的层次
**
** eg: c(0)->Lua(1)->Lua(2)->c()->Lua(1)->Lua(2)->Lua(3)->c(0)->Lua(1)
** 某次Lua调用结束，--nexeccalls，如果nexeccalls==0，表示当前lua调用链结束了，需要跳出luaV_execute函数
** 大于0表示本Lua调用结束后，上一层必然还是Lua函数，需要进入reentry点
*/
void luaV_execute (lua_State *L, int nexeccalls) {
  LClosure *cl;
  StkId base;
  TValue *k;
  const Instruction *pc;
 reentry:  /* entry point */
  lua_assert(isLua(L->ci));

  /* KEYCODE vm执行的关键参数:base,top,pc,savedpc, closure,k, L->ci,
  ** 后续因为call和return等切换调用栈时，必须正确处理上述参数
  */
  pc = L->savedpc;
  cl = &clvalue(L->ci->func)->l;
  base = L->base;
  k = cl->p->k;	/* locvars 仅在编译阶段/调试库中有效，虚拟机运行阶段无效(已编码到pc中) */
  
  /* main loop of interpreter */
  for (;;) {
    const Instruction i = *pc++;	/* 等效：*(pc++) */
    StkId ra;
   /* 运行钩子逻辑 */
    if ((L->hookmask & (LUA_MASKLINE | LUA_MASKCOUNT)) &&
        (--L->hookcount == 0 || L->hookmask & LUA_MASKLINE)) {
      traceexec(L, pc);
      if (L->status == LUA_YIELD) {  /* did hook yield? */
        L->savedpc = pc - 1;
        return;
      }
      base = L->base;
    }
    /* warning!! several(某些) calls may realloc the stack and invalidate `ra' */
    ra = RA(i);
    lua_assert(base == L->base && L->base == L->ci->base);
    lua_assert(base <= L->top && L->top <= L->stack + L->stacksize);
    lua_assert(L->top == L->ci->top || luaG_checkopenop(i));	/* luaG_checkopenop()蛮有意思的，需要彻底读懂(配合相关的指令逻辑一起看),看不懂则等看完相关指令后再看 */
    switch (GET_OPCODE(i)) {
      case OP_MOVE: {
        setobjs2s(L, ra, RB(i));
        continue;
      }
      case OP_LOADK: {
        setobj2s(L, ra, KBx(i));
        continue;
      }
      case OP_LOADBOOL: {
        setbvalue(ra, GETARG_B(i));
        if (GETARG_C(i)) pc++;  /* skip next instruction (if C) */
        continue;
      }
      case OP_LOADNIL: {
        TValue *rb = RB(i);
        do {
          setnilvalue(rb--);
        } while (rb >= ra);
        continue;
      }
      case OP_GETUPVAL: {
        int b = GETARG_B(i);
        setobj2s(L, ra, cl->upvals[b]->v);
        continue;
      }
      case OP_GETGLOBAL: {
        TValue g;
        TValue *rb = KBx(i);
        sethvalue(L, &g, cl->env);
        lua_assert(ttisstring(rb));	/* 全局变量名类型必须是TString */
        Protect(luaV_gettable(L, &g, rb, ra));
        continue;
      }
      case OP_GETTABLE: {
        Protect(luaV_gettable(L, RB(i), RKC(i), ra));
        continue;
      }
      case OP_SETGLOBAL: {
        TValue g;
        sethvalue(L, &g, cl->env);
        lua_assert(ttisstring(KBx(i)));
        Protect(luaV_settable(L, &g, KBx(i), ra));
        continue;
      }
      case OP_SETUPVAL: {
        UpVal *uv = cl->upvals[GETARG_B(i)];
        setobj(L, uv->v, ra);
        luaC_barrier(L, uv, ra);
        continue;
      }
      case OP_SETTABLE: {
        Protect(luaV_settable(L, ra, RKB(i), RKC(i)));
        continue;
      }
      case OP_NEWTABLE: {
        int b = GETARG_B(i);
        int c = GETARG_C(i);
        sethvalue(L, ra, luaH_new(L, luaO_fb2int(b), luaO_fb2int(c)));
        Protect(luaC_checkGC(L));
        continue;
      }
      case OP_SELF: {
        StkId rb = RB(i);	/* 拿到self.sub中的self指代的表 */
        setobjs2s(L, ra+1, rb);	/* 将上述表self存起来 */
        Protect(luaV_gettable(L, rb, RKC(i), ra)); /* 计算self.sub的值 */
        continue;
      }
      case OP_ADD: {
        arith_op(luai_numadd, TM_ADD);
        continue;
      }
      case OP_SUB: {
        arith_op(luai_numsub, TM_SUB);
        continue;
      }
      case OP_MUL: {
        arith_op(luai_nummul, TM_MUL);
        continue;
      }
      case OP_DIV: {
        arith_op(luai_numdiv, TM_DIV);
        continue;
      }
      case OP_MOD: {
        arith_op(luai_nummod, TM_MOD);
        continue;
      }
      case OP_POW: {
        arith_op(luai_numpow, TM_POW);
        continue;
      }
      case OP_UNM: {
        TValue *rb = RB(i);
        if (ttisnumber(rb)) {
          lua_Number nb = nvalue(rb);
          setnvalue(ra, luai_numunm(nb));
        }
        else {
          Protect(Arith(L, ra, rb, rb, TM_UNM));
        }
        continue;
      }
      case OP_NOT: {
        int res = l_isfalse(RB(i));  /* next assignment may change this value */
        setbvalue(ra, res);
        continue;
      }
      case OP_LEN: {
        const TValue *rb = RB(i);
        switch (ttype(rb)) {
          case LUA_TTABLE: {
            setnvalue(ra, cast_num(luaH_getn(hvalue(rb))));
            break;
          }
          case LUA_TSTRING: {
            setnvalue(ra, cast_num(tsvalue(rb)->len));
            break;
          }
          default: {  /* try metamethod */
            Protect(
              if (!call_binTM(L, rb, luaO_nilobject, ra, TM_LEN))
                luaG_typeerror(L, rb, "get length of");
            )
          }
        }
        continue;
      }
      case OP_CONCAT: {
        int b = GETARG_B(i);
        int c = GETARG_C(i);
        Protect(luaV_concat(L, c-b+1, c); luaC_checkGC(L));
        setobjs2s(L, RA(i), base+b);
        continue;
      }
      case OP_JMP: {
        dojump(L, pc, GETARG_sBx(i));
        continue;
      }
	  	/* KEYCODE 重点，难点，代表性的指令 
	  	** if ((RK(B) == RK(C)) ~= A) then pc++
	  	** OP_EQ后面紧跟着是跳转指令，这里猜测，跳转的值Bx应该短1，因为后面又进行了pc++
	  	*/
      case OP_EQ: {
        TValue *rb = RKB(i);
        TValue *rc = RKC(i);
        Protect(
          if (equalobj(L, rb, rc) == GETARG_A(i))
            dojump(L, pc, GETARG_sBx(*pc));
        )
        pc++;
        continue;
      }
      case OP_LT: {
        Protect(
          if (luaV_lessthan(L, RKB(i), RKC(i)) == GETARG_A(i))
            dojump(L, pc, GETARG_sBx(*pc));
        )
        pc++;
        continue;
      }
      case OP_LE: {	
        Protect(
          if (lessequal(L, RKB(i), RKC(i)) == GETARG_A(i))
            dojump(L, pc, GETARG_sBx(*pc));
        )
        pc++;
        continue;
      }
      case OP_TEST: {
        if (l_isfalse(ra) != GETARG_C(i))
          dojump(L, pc, GETARG_sBx(*pc));
        pc++;
        continue;
      }
      case OP_TESTSET: {
        TValue *rb = RB(i);
        if (l_isfalse(rb) != GETARG_C(i)) {
          setobjs2s(L, ra, rb);
          dojump(L, pc, GETARG_sBx(*pc));
        }
        pc++;
        continue;
      }
      case OP_CALL: {	/* R(A), ... ,R(A+C-2) := R(A)(R(A+1), ... ,R(A+B-1)) */
        int b = GETARG_B(i);	// 参数个数
        int nresults = GETARG_C(i) - 1;	// 期待的返回值个数 C:0(...), 1:(期待返回0个)，2:(期待返回1个)
        
        /* 当传入的参数数量明确时，移动top,
        ** 不明确时，OP_VARARG指令中已确定了top的位置 
        ** 故而本block之后，L->top都是指向了最后一个参数的"位置",也是告知被调用函数，我已经准备好了你要的参数且top指针已指到相应的位置了
        */
        if (b != 0) 
			L->top = ra+b;  /* else previous instruction set top(OP_VARARG指令已经准备好了L->top的位置) */
		
        L->savedpc = pc;	/* 记下原本接下来要执行的下一条指令 */
        switch (luaD_precall(L, ra, nresults)) {
          case PCRLUA: {
            nexeccalls++;
            goto reentry;  /* restart luaV_execute over new Lua function */
          }
          case PCRC: {
            /* it was a C function (`precall' called it); adjust results */
            if (nresults >= 0)	
				L->top = L->ci->top;	/* C调用结束，恢复本lua函数原本的top */
			else {
				//没有else，否则就是tailcall指令了?（tailcall后面的return给收尾了或者是setlist指令(local tbl = {fun()})
			}
            base = L->base;
            continue;
          }
          default: {
            return;  /* yield */
          }
        } 
      }
      case OP_TAILCALL: {	/* 其后跟着OP_RETURN，结合两个指令一起看(for c'fun call) */
	  	/* A B C return R(A)(R(A+1), ... ,R(A+B-1)) */
        int b = GETARG_B(i);
        if (b != 0) L->top = ra+b;  /* else previous instruction set top */
        L->savedpc = pc;
        lua_assert(GETARG_C(i) - 1 == LUA_MULTRET);	/* 尾调用的定义中：必须返回其调用返回的所有值，所以这里C必须为0 */
        switch (luaD_precall(L, ra, LUA_MULTRET)) {
          case PCRLUA: {	/* 这个block{}还没看懂 */
            /* tail call: put new frame in place of previous one */
            CallInfo *ci = L->ci - 1;  /* previous frame */
            int aux;
            StkId func = ci->func;
            StkId pfunc = (ci+1)->func;  /* previous function index */
            if (L->openupval) luaF_close(L, ci->base);
            L->base = ci->base = ci->func + ((ci+1)->base - pfunc);
            for (aux = 0; pfunc+aux < L->top; aux++)  /* move frame down */
              setobjs2s(L, func+aux, pfunc+aux);
            ci->top = L->top = func+aux;  /* correct top */
            lua_assert(L->top == L->base + clvalue(func)->l.p->maxstacksize);
            ci->savedpc = L->savedpc;
            ci->tailcalls++;  /* one more call lost */
            L->ci--;  /* remove new frame */
            goto reentry;
          }
          case PCRC: {  /* it was a C function (`precall' called it) */
            base = L->base;	/* restore base */
            continue;
          }
          default: {
            return;  /* yield */
          }
        }
      }
      case OP_RETURN: {
	  	/* return R(A), ... ,R(A+B-2) */
        int b = GETARG_B(i);	/* 0：返回所有值，1：返回1个值，2：返回2个值 ... */
        if (b != 0) 
			L->top = ra+b-1;	/* 以便确定返回值的确切个数 */
        if (L->openupval) luaF_close(L, base);
        L->savedpc = pc;
        b = luaD_poscall(L, ra);
        if (--nexeccalls == 0)  /* was previous function running `here'? Lua层面的调用结束了 */
          return;  /* no: return */
        else {  /* yes: continue its execution */
          if (b) L->top = L->ci->top;	/* 不是tailcall的返回，这里更新L->top */
          lua_assert(isLua(L->ci)); /* 根据nexeccalls来判断 */
          lua_assert(GET_OPCODE(*((L->ci)->savedpc - 1)) == OP_CALL);	/* 上一个指令必然是call? */
          goto reentry;
        }
      }
      case OP_FORLOOP: {	/* 先看 OP_FORPREP 指令 */
        lua_Number step = nvalue(ra+2);
        lua_Number idx = luai_numadd(nvalue(ra), step); /* increment index */
        lua_Number limit = nvalue(ra+1);
        if (luai_numlt(0, step) ? luai_numle(idx, limit)
                                : luai_numle(limit, idx)) {
          dojump(L, pc, GETARG_sBx(i));  /* jump back */
          setnvalue(ra, idx);  /* update internal index... */
          setnvalue(ra+3, idx);  /* ...and external index 这个idx才是暴露给for循环里面的i(for i = 0; 10; 1) */ 
        }
        continue;
      }
      case OP_FORPREP: {
        const TValue *init = ra;
        const TValue *plimit = ra+1;
        const TValue *pstep = ra+2;
        L->savedpc = pc;  /* next steps may throw errors */
        if (!tonumber(init, ra))
          luaG_runerror(L, LUA_QL("for") " initial value must be a number");
        else if (!tonumber(plimit, ra+1))
          luaG_runerror(L, LUA_QL("for") " limit must be a number");
        else if (!tonumber(pstep, ra+2))
          luaG_runerror(L, LUA_QL("for") " step must be a number");
        setnvalue(ra, luai_numsub(nvalue(ra), nvalue(pstep)));	/* 这里提前-=step */
        dojump(L, pc, GETARG_sBx(i));	/* 跳到cond判断那里 */
        continue;
      }
      case OP_TFORLOOP: {
	  	/* 编译模块保证了ra+3是个有意义的参数 
	  	** next函数会吃掉传入的参数，所以这里CP了一份
	    */
	    /* 结合 http://shankusu.me/lua/ANo-FrillsIntroductiontoLua51VMInstructions/ 文档来看，更容易理解 */
        StkId cb = ra + 3;  /* call base */
        setobjs2s(L, cb+2, ra+2);
        setobjs2s(L, cb+1, ra+1);
        setobjs2s(L, cb, ra);
        L->top = cb+3;  /* func. + 2 args (state and index) */
        Protect(luaD_call(L, cb, GETARG_C(i)));
        L->top = L->ci->top;
        cb = RA(i) + 3;  /* previous call may change the stack */
        if (!ttisnil(cb)) {  /* continue loop? */
          setobjs2s(L, cb-1, cb);  /* save control variable */
          dojump(L, pc, GETARG_sBx(*pc));  /* jump back */
        }
        pc++;
        continue;
      }
      case OP_SETLIST: {	/* local t = {...} 本指令之前可能会有一条vararg，所以结合vararg来理解本block的代码 */
	  	/* A B C	R(A)[(C-1)*FPF+i] := R(A+i), 1 <= i <= B */
        int n = GETARG_B(i);
        int c = GETARG_C(i);
        int last;
        Table *h;
        if (n == 0) {	
          n = cast_int(L->top - ra) - 1;	/* 计算确切的参数个数 */
          L->top = L->ci->top;	/* OP_VARARG指令L->top已经指向了{...}不定参数的最后一个slot的位置以便求n,这里将其复原 */
        }
        if (c == 0) c = cast_int(*pc++);	/* 这行代码最好有个印象 */
        runtime_check(L, ttistable(ra));	/* 编译模块出错了 */
        h = hvalue(ra);
        last = ((c-1)*LFIELDS_PER_FLUSH) + n;	/* 计算当前能确定的数组下标的最大值 */
        if (last > h->sizearray)  /* needs more space?  数组区域大小不够，需扩展*/
          luaH_resizearray(L, h, last);  /* pre-alloc it at once */
        for (; n > 0; n--) {
          TValue *val = ra+n;
          setobj2t(L, luaH_setnum(L, h, last--), val);
          luaC_barriert(L, h, val);
        }
        continue;
      }
      case OP_CLOSE: {
	  	/* close all variables in the stack up to (>=) R(A) 编译模块如何确定参数A？*/
        luaF_close(L, ra);
        continue;
      }
      case OP_CLOSURE: {
	  	/* A Bx	R(A) := closure(KPROTO[Bx], R(A), ... ,R(A+n)) */
        Proto *p;
        Closure *ncl;
        int nup, j;
        p = cl->p->p[GETARG_Bx(i)];	/* 找到对应的proto */
        nup = p->nups;
        ncl = luaF_newLclosure(L, nup, cl->env);
        ncl->l.p = p;
		/* 下面的block尚未完全看懂 */
        for (j=0; j<nup; j++, pc++) {
          if (GET_OPCODE(*pc) == OP_GETUPVAL)
            ncl->l.upvals[j] = cl->upvals[GETARG_B(*pc)];
          else {
            lua_assert(GET_OPCODE(*pc) == OP_MOVE);
            ncl->l.upvals[j] = luaF_findupval(L, base + GETARG_B(*pc));
          }
        }
        setclvalue(L, ra, ncl);
        Protect(luaC_checkGC(L));
        continue;
      }
      case OP_VARARG: {
	  	/* A B	R(A), R(A+1), ..., R(A+B-1) = vararg */
        int b = GETARG_B(i) - 1;
        int j;
        CallInfo *ci = L->ci;
        int n = cast_int(ci->base - ci->func) - cl->p->numparams - 1;	/* 本次函数调用传入的不定参数的个数eg: funA(a,b, ...) funA */
        if (b == LUA_MULTRET) {
          Protect(luaD_checkstack(L, n));
          ra = RA(i);  /* previous call may change the stack */
          b = n;	/* 出现在 local tbl = {...} 或者 funA(...) 需要拷贝所有的不定参数的地方 */

		  /* 为可能即将到来的C/lua函数调用做准备，(L->top-func可知即将发生的函数调用实际上有多少个传入参数) 
		  ** 
		  ** local tbl={...} OP_SETLIST指令也用到了L->top，故而可以推断出，这里L->top标记了实际上...携带的参数个数
		  ** 以便其它指令能准确的执行(主要是获取..参数个数)，这里将实际传入的参数个数通过L->top计算好，避免其它指令再去计算一遍
		  ** 其它指令用完L->top后需将其复原
		  */
          L->top = ra + n; 
        }
		/* 将不定参数赋值给指定的对象？？？
		** local a, b = ...
		** 不定参数数量不足则补nil
		*/
        for (j = 0; j < b; j++) {
          if (j < n) {	/* 本函数的不定参数的个数还能满足ra+j代表的dst寄存器 */
            setobjs2s(L, ra + j, ci->base - n + j);
          }
          else {
            setnilvalue(ra + j);	/* local a, b = ... 本函数实际上只收到了一个不定参数，那么不足的部分(b)就要补nil值了 */
          }
        }
        continue;
      }
    }
  }
}

